[{"id":"xianguo",
"tips":"鲜果",
 "goodsId":["xianguo1","xianguo2","xianguo3","xianguo4","xianguo5"],
"src":["xianguo1.jpg","xianguo2.jpg","xianguo3.jpg","xianguo4.jpg","xianguo5.jpg"],
"dec":["[预定特价]阿克苏冰糖心苹果12个礼盒装-约6-7斤每个85m...","新疆皮亚曼大石榴 8个5斤顺丰包邮-鲜果-十月特价","新疆克瑞森无籽葡萄2kg-新品特价-鲜果","新疆有机红提葡萄（2kg）-鲜果上市特价","【预定特价】阿克苏冰糖心苹果家庭装-约10斤21-24个-每个75mm以上-11月中发货-鲜果"],
"price":["119.00","118.00","99.00","89.00","66.00"]},

{"id":"gz",
"tips":"古皂",
"goodsId":["gz1","gz2","gz3","gz4","gz5","gz6","gz7","gz8","gz9","gz10","gz11","gz12","gz13","gz14","gz15","gz16","gz17","gz18","gz19","gz20","gz21","gz22","gz23","gz24","gz25","gz26"],
"src":["gz1.jpg","gz2.jpg","gz3.jpg","gz4.jpg","gz5.jpg","gz6.jpg","gz7.jpg","gz8.jpg","gz9.jpg","gz10.jpg","gz11.jpg","gz12.jpg","gz13.jpg","gz14.jpg","gz15.jpg","gz16.jpg","gz17.jpg","gz18.jpg","gz19.jpg","gz20.jpg","gz21.jpg","gz22.jpg","gz23.jpg","gz24.jpg","gz25.jpg","gz26.jpg"],
"dec":["【十月特价】阿勒颇钻石级限量版古皂210±10g（窖藏五年，原价218元）","油性肌肤祛痘美发古皂套餐（清颜古皂230克+橘花精油皂90克，原价207元）--特价","古皂亲子特价套餐（特级黑橄榄皂200克+蜂蜜羊奶皂90克，原价257元）","护发美白特价套餐（特级黑橄榄四年古皂100克+玫瑰花瓣皂90克）","大马士革乳木果精油橄榄油手工精油皂_90克","橄榄油蜂蜜羊奶手工精油皂90克","阿勒颇特级近头层黑橄榄油四年古皂210±10g-glz002","阿勒颇清颜古皂（两年窖藏）210±10g，新品特价","大马士革茉莉橄榄手工皂_90克-jyz002","大马士革石榴籽油橄榄手工精油皂_90克-glz007","阿勒颇榄桂液体皂200ml","希腊丝绒海绵_4英寸_古皂配套","希腊蜂窝海绵_5.5英寸_古皂配套","大马士革黑种草籽油橄榄手工精油皂_90克-jyz005","大马士革香草橄榄手工精油皂_90克-glz008","大马士革薰衣草橄榄手工精油皂_90克-jyz003","大马士革紫罗兰橄榄手工精油皂_90克-jyz004","阿勒颇橄榄古皂（窖藏一年）210克","大马士革玫瑰花瓣橄榄手工精油皂_90克","大马士革燕麦橄榄手工精油皂_90克","大马士革橘花精油橄榄油手工精油皂_90克","大马士革杏仁油橄榄手工精油皂_90克","干性中性肌肤祛痘美发古皂套餐（清颜古皂230克+黑种草籽油90克，原价207元）--特价","阿勒颇特级近头层黑橄榄油四年古皂半块（100克）-glz004","大马士革仙人掌籽橄榄手工精油皂_90克-jyz006","大马士革亚麻籽油橄榄手工精油皂_90克"],
"price":["191.00","186.00","230.00","152.00","79.00","79.00","178.00","128.00","69.00","79.00","78.00","98.00","168.00","79.00","79.00","69.00","79.00","88.00","79.00","79.00","79.00","79.00","186.00","90.00","79.00","79.00"]},
{"id":"rou",
"tips":"牛羊肉",
 "goodsId":["rou1","rou2","rou3","rou4","rou5","rou6","rou7","rou8","rou9"],
"src":["rou1.jpg","rou2.jpg","rou3.jpg","rou4.jpg","rou5.jpg","rou6.jpg","rou7.jpg","rou8.jpg","rou9.jpg"],
"dec":["牦牛肉牛排特价套餐（牛肉3斤，牛排1kg，每斤折约39元） -牛羊肉","藏羊肉羊排特价套餐（羊肉3斤，羊排1kg，每斤折约29元） -牛羊肉","【十月特价】红烧牦牛尾-牛羊肉熟食","【双11特价】清河源卤牦牛腱（280g/袋）-牛羊肉熟食","清真卤牛肉小包装香辣味（110g,两袋以上特价每袋15元）-牛羊肉-熟食","牦牛肉一斤（3斤以上每斤特价39.9元）-牛羊肉","藏羊肉一斤（3斤以上每斤特价29.9元）-牛羊肉","藏羊排1kg（原价63元，十月特价折每斤约29.9元）-牛羊肉","牦牛肋排1kg（原价89元，十月特价折每斤约39.9元） -牛羊肉"],
"price":["199.00","149.00","45.00","65.00","24.50","45.00","39.90","59.90","79.90"]},
{"id":"fengmi",
"tips":"蜂蜜",
 "goodsId":["fengmi1","fengmi2","fengmi3","fengmi4","fengmi5","fengmi6","fengmi7","fengmi8","fengmi9","fengmi10","fengmi11","fengmi12","fengmi13","fengmi14","fengmi15","fengmi16","fengmi17","fengmi18","fengmi19","fengmi20","fengmi21","fengmi22","fengmi23","fengmi24","fengmi25"],
"src":["fengmi1.jpg","fengmi2.jpg","fengmi3.jpg","fengmi4.jpg","fengmi5.jpg","fengmi6.jpg","fengmi7.jpg","fengmi8.jpg","fengmi9.jpg","fengmi10.jpg","fengmi11.jpg","fengmi12.jpg","fengmi13.jpg","fengmi14.jpg","fengmi15.jpg","fengmi16.jpg","fengmi17.jpg","fengmi18.jpg","fengmi19.jpg","fengmi20.jpg","fengmi21.jpg","fengmi22.jpg","fengmi23.jpg","fengmi24.jpg","fengmi25.jpg"],
"dec":["天山药草蜂蜜500克(2瓶起特价95折64.6元)","天然老巢蜜-蜂蜜(400g/盒，全国包邮)乐扣装-新品特价","新疆黑蜂百花蜂蜜10g*10小袋便携装-蜂蜜-十月特价","古皂亲子特价套餐（特级黑橄榄皂200克+蜂蜜羊奶皂90克，原价257元）","【双11特价】喀什玫瑰花酱精华-手工制作无添加150g -蜂蜜果酱类","【双11特价】喀什玫瑰花酱-手工无添加320g-蜂蜜果酱类","【预定特价】罗布泊野生骆驼刺糖蜜500g-蜂蜜-约11月12日发货","新疆黑蜂老蜂巢蜂蜜450g","天山深山原蜜300克-蜂蜜","【十月特价】便携装天山药草蜂蜜15克*10袋","橄榄油蜂蜜羊奶手工精油皂90克","新疆黑蜂野菊花蜂蜜500g-蜂蜜","【十月特价】天山白蜂蜜（高原菜花蜜）500克，原价42元","【十月特价】向日葵蜂蜜500克（原价59元）","天山药草蜂蜜礼盒（500g*3）-十月特价","天然蜂王浆250克（冷链储运）-蜂蜜产品","【十月特价】椴树蜜-蜂蜜1kg（原价98元）","天山白蜂蜜礼盒（菜花蜜），500g*3瓶-十月特价","【十月特价】马琳蜂蜜果酱（308g，原价36元）","野生沙枣纯蜂蜜500克（2瓶起九折特价89元）","薰衣草蜂蜜500克（2瓶起特价59元）","蜂胶75克（2瓶起特价95折150元）-蜂蜜产品","新疆枸杞蜂蜜500g（2瓶起特价95折65.5元）","新疆天山野山花蜂蜜（黑蜂蜜）500克（2瓶起特价95折55元）","云南土蜂蜜500克（2瓶起特价95折103.5元）"],
"price":["68.00","109.00","29.9.00","230.00","60.00","40.00","118.00","139.00","98.00","33.00","79.00","69.90","39.90","55.00","190.00","89.90","128.00","208","33.00","99.00","69.00","158.00","69.00"," 58.00","109.00"]},
{"id":"xuejv",
"tips":"雪菊",
 "goodsId":["xuejv1","xuejv2","xuejv3","xuejv4","xuejv5"],
"src":["xuejv1.jpg","xuejv2.jpg","xuejv3.jpg","xuejv4.jpg","xuejv5.jpg"],
"dec":["【十月特价】昆仑雪菊（大罐80克，原价100元，特价86元）","昆仑雪菊礼盒装（250克）-十月特价","昆仑雪菊--50克/小罐","雪菊礼盒装（150克）","昆仑雪菊胎菊80克"],
"price":["86.00","345.00","67.00","208.00","89.00"]},
{"id":"liangyou",
"tips":"粮油",
 "goodsId":["liangyou1","liangyou2","liangyou3","liangyou4","liangyou5","liangyou6","liangyou7","liangyou8","liangyou9","liangyou10","liangyou11","liangyou12","liangyou13","liangyou14","liangyou15","liangyou16","liangyou17","liangyou18","liangyou19","liangyou20","liangyou21","liangyou22","liangyou23","liangyou24","liangyou25","liangyou26","liangyou27","liangyou28","liangyou29"],
"src":["liangyou1.jpg","liangyou2.jpg","liangyou3.jpg","liangyou4.jpg","liangyou5.jpg","liangyou6.jpg","liangyou7.jpg","liangyou8.jpg","liangyou9.jpg","liangyou10.jpg","liangyou11.jpg","liangyou12.jpg","liangyou13.jpg","liangyou14.jpg","liangyou15.jpg","liangyou16.jpg","liangyou17.jpg","liangyou18.jpg","liangyou19.jpg","liangyou20.jpg","liangyou21.jpg","liangyou22.jpg","liangyou23.jpg","liangyou24.jpg","liangyou25.jpg","liangyou26.jpg","liangyou27.jpg","liangyou28.jpg","liangyou29.jpg"],
"dec":["五常稻花香有机大米-2016新米-2.5kg（两袋以上每袋特价69.90元，11月2日起发货）-粮油","【十月特价】新疆有机小麦粉（面粉，2kg，出粉率75%，原价65元）-粮油","新疆伊犁察布查尔有机大米1kg（五袋以上每袋特价49元）-粮油","精选16种杂粮礼盒-十月特价（原价243.3元）-粮油","【十月特价】有机绿豆400g/盒-粮油（原价16.90元）","【十月特价】有机绿豆400g/盒-粮油（原价16.90元）","【十月特价】有机绿豆400g/盒-粮油（原价16.90元）","【十月特价】有机绿豆400g/盒-粮油（原价16.90元）","【十月特价】有机绿豆400g/盒-粮油（原价16.90元）","【十月特价】有机绿豆400g/盒-粮油（原价16.90元）","【十月特价】有机绿豆400g/盒-粮油（原价16.90元）","【十月特价】有机绿豆400g/盒-粮油（原价16.90元）","【十月特价】有机绿豆400g/盒-粮油（原价16.90元）","【十月特价】有机绿豆400g/盒-粮油（原价16.90元）","【十月特价】有机绿豆400g/盒-粮油（原价16.90元）","【十月特价】有机绿豆400g/盒-粮油（原价16.90元）","【十月特价】有机绿豆400g/盒-粮油（原价16.90元）","【十月特价】有机绿豆400g/盒-粮油（原价16.90元）","【十月特价】有机绿豆400g/盒-粮油（原价16.90元）","【十月特价】有机绿豆400g/盒-粮油（原价16.90元）","【十月特价】有机绿豆400g/盒-粮油（原价16.90元）","【十月特价】有机绿豆400g/盒-粮油（原价16.90元）","【十月特价】有机绿豆400g/盒-粮油（原价16.90元）","【十月特价】有机绿豆400g/盒-粮油（原价16.90元）","【十月特价】有机绿豆400g/盒-粮油（原价16.90元）","【十月特价】有机绿豆400g/盒-粮油（原价16.90元）","【十月特价】有机绿豆400g/盒-粮油（原价16.90元）","【十月特价】有机绿豆400g/盒-粮油（原价16.90元）","【十月特价】有机绿豆400g/盒-粮油（原价16.90元）"],
"price":["78.00","58.00","58.00","215.10","15.90","15.90","15.90","15.90","15.90","15.90","15.90","15.90","15.90","15.90","15.90","15.90","15.90","15.90","15.90","15.90","15.90","15.90","15.90","15.90","15.90","15.90","15.90","15.90","15.90"]},
{"id":"shicai",
"tips":"食材",
 "goodsId":["shicai1","shicai2","shicai3","shicai4","shicai5","shicai6","shicai7","shicai8","shicai9","shicai10","shicai11","shicai12"],
"src":["shicai1.jpg","shicai2.jpg","shicai3.jpg","shicai4.jpg","shicai5.jpg","shicai6.jpg","shicai7.jpg","shicai8.jpg","shicai9.jpg","shicai10.jpg","shicai11.jpg","shicai12.jpg"],
"dec":["【十月特价】特级无硫兰州甜百合干240克/盒（原价99元）-食材","【十月特价】建宁莲子-袋装240克（原价40元）-食材","【十月特价】东北黑木耳-袋装200克（原价43元）-菌菇-食材","【十月特价】古田银耳-袋装80克（原价12元）-食材","特级小香菇-袋装200克-菌菇-食材","特级桂圆干-袋装500克-食材-干果","小罐特级枸杞（200克）-食材-干果","【双节特价】新疆特级枸杞-袋装280克-食材-干果","新疆一级枸杞-袋装280克-食材-干果","虫草花（100克/袋）-菌菇-食材","特级花菇-袋装200克-菌菇-食材","云南昭通巧家小碗红糖（600克/瓶）-食材"],
"price":["97.00","38.50","39.90","10.50","43.00","33.00","33.50","39.50","37.00","88.00","43.00","42.00"]},
{"id":"shiyongyou",
"tips":"食用油",
 "goodsId":["shiyongyou1","shiyongyou2","shiyongyou3","shiyongyou4","shiyongyou5"],
"src":["shiyongyou1.jpg","shiyongyou2.jpg","shiyongyou3.jpg","shiyongyou4.jpg","shiyongyou5.jpg"],
"dec":["长寿山茶油（500ml/瓶，单瓶简装）-粮油-食用油","清香型山茶油（500ml/瓶，单瓶简装）-粮油-食用油","古法压榨双低菜籽油（1.8L/盒，2盒以上每盒56元）-粮油-食用油","古法压榨纯胡麻油（1.8L/盒）-粮油-食用油","古法压榨纯胡麻油（1.8L/盒）-粮油-食用油"],
"price":["116.00","96.00","58.00","128.00","79.00"]},
{"id":"shushi",
"tips":"熟食",
 "goodsId":["shushi1","shushi2","shushi3","shushi4","shushi5","shushi6"],
"src":["shushi1.jpg","shushi2.jpg","shushi3.jpg","shushi4.jpg","shushi5.jpg","shushi6.jpg"],
"dec":["【十月特价】红烧牦牛尾-牛羊肉熟食","【双11特价】清河源卤牦牛腱（280g/袋）-牛羊肉熟食","清真卤牛肉小包装香辣味（110g,两袋以上特价每袋15元）-牛羊肉-熟食","白家清真酸辣粉丝（碗装） 108g/碗--熟食","白家清真酸辣粉丝五连包108g*5/包，2包以上特价86折 -粮油-熟食","白家清真酸辣粉丝袋装（108g）5袋以上每袋3.2元-粮油-熟食"],
"price":["45.00","65.00","24.50","5.00","3.50","3.20"]},
{"id":"ganguo",
"tips":"干果",
 "goodsId":["ganguo1","ganguo2","ganguo3","ganguo4","ganguo5","ganguo6","ganguo7","ganguo8","ganguo9","ganguo10","ganguo11","ganguo12","ganguo13","ganguo14","ganguo15","ganguo16","ganguo17","ganguo18","ganguo19","ganguo20","ganguo21","ganguo22","ganguo23","ganguo24","ganguo25","ganguo26","ganguo27","ganguo28","ganguo29","ganguo30"],
"src":["ganguo1.jpg","ganguo2.jpg","ganguo3.jpg","ganguo4.jpg","ganguo5.jpg","ganguo6.jpg","ganguo7.jpg","ganguo8.jpg","ganguo9.jpg","ganguo10.jpg","ganguo11.jpg","ganguo12.jpg","ganguo13.jpg","ganguo14.jpg","ganguo15.jpg","ganguo16.jpg","ganguo17.jpg","ganguo18.jpg","ganguo19.jpg","ganguo20.jpg","ganguo21.jpg","ganguo22.jpg","ganguo23.jpg","ganguo24.jpg","ganguo25.jpg","ganguo26.jpg","ganguo27.jpg","ganguo28.jpg","ganguo29.jpg","ganguo30.jpg"],
"dec":["小罐特级黑桑葚干（120克）-干果","特级黑桑葚干-袋装180克-干果","小罐小无花果（200克）-干果","小无花果-袋装280克-干果","小罐绿葡萄干（200克）-干果","绿葡萄干-袋装280克-干果","绿葡萄干-袋装280克-干果","绿葡萄干-袋装280克-干果","绿葡萄干-袋装280克-干果","绿葡萄干-袋装280克-干果","绿葡萄干-袋装280克-干果","绿葡萄干-袋装280克-干果","绿葡萄干-袋装280克-干果","绿葡萄干-袋装280克-干果","绿葡萄干-袋装280克-干果","绿葡萄干-袋装280克-干果","绿葡萄干-袋装280克-干果","绿葡萄干-袋装280克-干果","绿葡萄干-袋装280克-干果","绿葡萄干-袋装280克-干果","绿葡萄干-袋装280克-干果","绿葡萄干-袋装280克-干果","绿葡萄干-袋装280克-干果","绿葡萄干-袋装280克-干果","绿葡萄干-袋装280克-干果","绿葡萄干-袋装280克-干果","绿葡萄干-袋装280克-干果","绿葡萄干-袋装280克-干果","绿葡萄干-袋装280克-干果","绿葡萄干-袋装280克-干果"],
"price":["14.50","19.50","18.50","20.50","17.00","18.00","18.00","18.00","18.00","18.00","18.00","18.00","18.00","18.00","18.00","18.00","18.00","18.00","18.00","18.00","18.00","18.00","18.00","18.00","18.00","18.00","18.00","18.00","18.00","18.00"]},
{"id":"jianguo",
"tips":"坚果",
 "goodsId":["jianguo1","jianguo2","jianguo3","jianguo4","jianguo5","jianguo6","jianguo7","jianguo8","jianguo9","jianguo10","jianguo11","jianguo12","jianguo13","jianguo14","jianguo15","jianguo16","jianguo17","jianguo18"],
"src":["jianguo1.jpg","jianguo2.jpg","jianguo3.jpg","jianguo4.jpg","jianguo5.jpg","jianguo6.jpg","jianguo7.jpg","jianguo8.jpg","jianguo9.jpg","jianguo10.jpg","jianguo11.jpg","jianguo12.jpg","jianguo13.jpg","jianguo14.jpg","jianguo15.jpg","jianguo16.jpg","jianguo17.jpg","jianguo18.jpg"],
"dec":["小罐碧根果（奶油味，150克）-坚果","碧根果（奶油味）-袋装280克-坚果","小罐东北红松子（200克）-坚果","东北野生红松子-袋装280克-坚果","东北野生红松子-袋装280克-坚果","东北野生红松子-袋装280克-坚果","东北野生红松子-袋装280克-坚果","东北野生红松子-袋装280克-坚果","东北野生红松子-袋装280克-坚果","东北野生红松子-袋装280克-坚果","东北野生红松子-袋装280克-坚果","东北野生红松子-袋装280克-坚果","东北野生红松子-袋装280克-坚果","东北野生红松子-袋装280克-坚果","东北野生红松子-袋装280克-坚果","东北野生红松子-袋装280克-坚果","东北野生红松子-袋装280克-坚果","东北野生红松子-袋装280克-坚果"],
"price":["15.00","25.00","27.00","20.50","39.00","18.00","18.00","18.00","18.00","18.00","18.00","18.00","18.00","18.00","18.00","18.00","18.00","18.00"]},
{"id":"fengwangjiang",
"tips":"蜂王浆",
 "goodsId":["fengwangjiang1"],
"src":["fengwangjiang1.jpg"],
"dec":["天然蜂王浆250克（冷链储运）-蜂蜜产品"],
"price":["190.00"]},
{"id":"fengjiao",
"tips":"蜂胶",
 "goodsId":["fengjiao1"],
"src":["fengjiao1.jpg"],
"dec":["蜂胶75克（2瓶起特价95折150元）-蜂蜜产品"],
"price":["158.00"]},
{"id":"zanghonghua",
"tips":"藏红花",
 "goodsId":["zanghonghua1"],
"src":["zanghonghua1.jpg"],
"dec":["【十月特价】伊朗原产藏红花（3克，可泡茶用，原价119元）"],
"price":["109.00"]},
{"id":"meiguihuacha",
"tips":"玫瑰花茶",
 "goodsId":["meiguihuacha1"],
"src":["meiguihuacha1.jpg"],
"dec":["玫瑰花茶（小罐60克）"],
"price":["25.00"]},
{"id":"lingshi",
"tips":"零食",
 "goodsId":["lingshi1","lingshi2","lingshi3","lingshi4","lingshi5","lingshi6","lingshi7"],
"src":["lingshi1.jpg","lingshi2.jpg","lingshi3.jpg","lingshi4.jpg","lingshi5.jpg","lingshi6.jpg","lingshi7.jpg"],
"dec":["切糕脆150g-零食","【十月特价】大枣夹核桃仁（268g/袋，内为独立小包装，原价52元）-零食","巴旦木仁切糕-小包装100克-零食","综合味切糕-小包装100克-零食","核桃切糕-小包装100克-零食","红枣切糕-小包装100克-零食","综合、红枣、核桃、巴旦木四种切糕（新疆玛仁糖）各100克-零食"],
"price":["28.00","49.90","23.00","17.50","22.00","19.50","79.90"]},
 {
  "id":"naifen",
  "tips":"奶粉",
  "goodsId":["naifen1","naifen2","naifen3","naifen4","naifen5","naifen6"],
  "src":["naifen1.jpg","naifen2.jpg","naifen3.jpg","naifen4.jpg","naifen5.jpg","naifen6.jpg"],
  "dec":["燎原全脂加糖耗牛奶粉","燎原全脂加糖耗牛奶粉礼盒 2罐装","燎原精装婴儿奶粉 900克/罐","燎原精装较大婴儿奶粉","燎原精装幼儿配方奶粉","燎原精装婴儿配方奶粉"],
  "price":["49.00","292.00","278.00","268.00","236.00","130.00"]
 },
 {
  "id":"guojiang",
  "tips":"果酱",
  "goodsId":["guojiang1","guojiang2","guojiang3","guojiang4","guojiang5","guojiang6"],
  "src":["guojiang1.jpg","guojiang2.jpg","guojiang3.jpg","guojiang4.jpg","guojiang5.jpg"],
  "dec":["【双11特价】喀什玫瑰花酱-手工无添加320g-蜂...","【特价】马琳蜂蜜果酱（308g，原价36元）","【双11特价】喀什玫瑰花酱-手工无添加320g-蜂...","【双11特价】喀什玫瑰花酱-手工无添加...","野酸梅果酱308g（原价36元）"],
  "price":["40.00","33.00","40.00","60.00","33.00"]
 },
 {
  "id":"chaye",
  "tips":"茶叶",
  "goodsId":["chaye1","chaye2","chaye3","chaye4","chaye5","chaye6","chaye7","chaye8","chaye9"],
  "src":["chaye1.jpg","chaye2.jpg","chaye3.jpg","chaye4.jpg","chaye5.jpg","chaye6.jpg"],
  "dec":["醉正红-正山红茶礼盒（3罐/盒 255g）-茶叶-特...","虎啸山野生红茶","虎啸岩大红袍","普洱茶-桶装普洱2010年熟茶（160g/桶）-茶叶","普洱茶-云南七子饼茶（宫廷贡饼1990年代 熟茶...","普洱茶-2013布朗山生茶（500g/饼）-茶叶","普洱茶-饼茶（7548）2014年生茶（357g/饼）-...","【特价】普洱茶-饼茶（7578）2015年熟茶","福鼎白茶-2014年太姥银针（350g/饼）-茶叶"],
  "price":["538.00","218.00","238.00","268.00","236.00","130.00","188.00","169.00","580.00"]
 },
 {
  "id":"jungu",
  "tips":"菌菇",
  "goodsId":["jungu1","jungu2","jungu3"],
  "src":["jungu1.jpg","jungu2.jpg","jungu3.jpg"],
  "dec":["东北黑木耳","特技花菇","虫草花"],
  "price":["538.00","218.00","88.00"]
 },
 {
 "id":"qiegao",
 "tips":"切糕",
 "goodsId":["qiegao1","qiegao2","qiegao3"],
 "src":["qiegao1.jpg","qiegao2.jpg","qiegao3.jpg"],
 "dec":["综合、红枣、核桃、巴旦木四种切糕（新疆玛仁...","巴旦木仁切糕-小包装100克-零食","综合味切糕-小包装100克-零食"],
 "price":["79.90","23.00","17.50"]
},
 {
  "id":"dazao",
  "tips":"大枣",
  "goodsId":["dazao1","dazao2","dazao3"],
  "src":["dazao1.jpg","dazao2.jpg","dazao3.jpg"],
  "dec":["和田大枣","新疆和田大枣三级","若羌灰枣"],
  "price":["255.50","39.00","39.50"]
 },
 {
  "id":"xinggan",
  "tips":"杏干",
  "goodsId":["xinggan1"],
  "src":["xinggan1.jpg"],
  "dec":["杏干"],
  "price":["36.00"]
 },
 {
  "id":"putaogan",
  "tips":"葡萄干",
  "goodsId":["putaogan1","putaogan2","putaogan3","putaogan4","putaogan5","putaogan6"],
  "src":["putaogan1.jpg","putaogan2.jpg","putaogan3.jpg","putaogan4.jpg","putaogan5.jpg","putaogan6.jpg"],
  "dec":["黑玫瑰葡萄干","红宝石葡萄干","红宝石葡萄干","巨无霸葡萄干","黑加仑葡萄干","葡萄干"],
  "price":["26.50","15.00","13.00","28.00","17.00","17.00"]
 },
 {
  "id":"gouqi",
  "tips":"枸杞",
  "goodsId":["gouqi1","gouqi2","gouqi3"],
  "src":["gouqi1.jpg","gouqi2.jpg","gouqi3.jpg"],
  "dec":["新疆一级枸杞","新疆一级枸杞","新疆特级枸杞"],
  "price":["37.00","37.00","43.00"]
 },
 {
  "id":"heigouqi",
  "tips":"黑枸杞",
  "goodsId":["heigouqi1"],
  "src":["heigouqi1.jpg"],
  "dec":["黑枸杞"],
  "price":["188.50"]
 },
 {
  "id":"sangshengan",
  "tips":"桑葚干",
  "goodsId":["sangshengan1"],
  "src":["putaogan1.jpg"],
  "dec":["桑葚干"],
  "price":["26.50"]
 },
 {
  "id":"baihegan",
  "tips":"百合干",
  "goodsId":["baihegan1"],
  "src":["baihegan1.jpg"],
  "dec":["百合干"],
  "price":["99.00"]
 },
 {
  "id":"zaojiahetao",
  "tips":"枣夹核桃",
  "goodsId":["zaojiahetao1"],
  "src":["zaojiahetao1.jpg"],
  "dec":["枣夹核桃"],
  "price":["52.50"]
 },
 {
  "id":"miantiao",
  "tips":"面条",
  "goodsId":["miantiao1"],
  "src":["miantiao1.jpg"],
  "dec":["兰州清真拉面"],
  "price":["11.50"]
 },
 {
  "id":"zaliang",
  "tips":"杂粮",
  "goodsId":["zaliang1"],
  "src":["zaliang1.jpg"],
  "dec":["杂粮"],
  "price":["6.50"]
 },
 {
  "id":"lihe",
  "tips":"礼盒",
  "goodsId":["lihe1","lihe2","lihe3","lihe4","lihe5","lihe6"],
  "src":["lihe1.jpg","lihe2.jpg","lihe3.jpg","lihe4.jpg","lihe5.jpg","lihe6.jpg"],
  "dec":["有机杂粮礼盒","白蜂蜜礼盒","药草蜂蜜礼盒","有机杂粮礼盒1","白蜂蜜礼盒2","药草蜂蜜礼盒3"],
  "price":["6.50","128.00","208.00","780.00","215.10","200.00"]
 }
]
